virtualpet/__init__.py
virtualpet/pet.py
virtualpet_game-0.1.2.dist-info/LICENSE
virtualpet_game-0.1.2.dist-info/METADATA
virtualpet_game-0.1.2.dist-info/WHEEL
virtualpet_game-0.1.2.dist-info/entry_points.txt
virtualpet_game-0.1.2.dist-info/top_level.txt
virtualpet_game-0.1.2.dist-info/RECORD
