Metadata-Version: 2.1
Name: virtualpet-game
Version: 0.1.2
Summary: An example of a package developed with pyenv, built with build using setuptools, uploaded to PyPI using twine, and distributed via pip.
Author-email: ritaziruihe <zh2266@nyu.edu>, Applejam-ovo <ql2138@nyu.edu>, ElaineR02 <pl2355@nyu.edu>, HannahLiang627 <zl3927@nyu.edu>
License: GNU GENERAL PUBLIC LICENSE
Project-URL: Homepage, https://github.com/software-students-fall2024/3-python-package-straight-a
Project-URL: Repository, https://github.com/software-students-fall2024/3-python-package-straight-a.git
Project-URL: Bug Tracker, https://github.com/software-students-fall2024/3-python-package-straight-a/issues
Keywords: python,package,build,tutorial
Classifier: Programming Language :: Python :: 3
Classifier: Intended Audience :: Education
Classifier: License :: OSI Approved :: GNU General Public License v3 (GPLv3)
Classifier: Operating System :: OS Independent
Requires-Python: >=3.7
License-File: LICENSE
Provides-Extra: dev
Requires-Dist: pytest; extra == "dev"
